CHANGELOG.md
README.md
servo/__init__.py
servo/api.py
servo/assembly.py
servo/checks.py
servo/cli.py
servo/configuration.py
servo/connector.py
servo/connectors/__init__.py
servo/connectors/kube_metrics.py
servo/connectors/kubernetes.py
servo/connectors/kubernetes_helpers/__init__.py
servo/connectors/kubernetes_helpers/base.py
servo/connectors/kubernetes_helpers/base_workload.py
servo/connectors/kubernetes_helpers/container.py
servo/connectors/kubernetes_helpers/deployment.py
servo/connectors/kubernetes_helpers/namespace.py
servo/connectors/kubernetes_helpers/pod.py
servo/connectors/kubernetes_helpers/replicaset.py
servo/connectors/kubernetes_helpers/service.py
servo/connectors/kubernetes_helpers/statefulset.py
servo/connectors/kubernetes_helpers/util.py
servo/connectors/opsani_dev.py
servo/connectors/prometheus.py
servo/connectors/scripts.py
servo/connectors/vegeta.py
servo/connectors/vegeta_target_schema.json
servo/connectors/wait.py
servo/encoders.py
servo/entry_points.py
servo/errors.py
servo/events.py
servo/fast_fail.py
servo/logging.py
servo/pubsub.py
servo/repeating.py
servo/runner.py
servo/servo.py
servo/telemetry.py
servo/types/__init__.py
servo/types/api.py
servo/types/core.py
servo/types/kubernetes.py
servo/types/settings.py
servo/types/slo.py
servo/utilities/__init__.py
servo/utilities/associations.py
servo/utilities/duration_str.py
servo/utilities/hashing.py
servo/utilities/inspect.py
servo/utilities/key_paths.py
servo/utilities/pydantic.py
servo/utilities/strings.py
servo/utilities/subprocess.py
servo/utilities/yaml.py
servox-25.3.0.dist-info/LICENSE
servox-25.3.0.dist-info/METADATA
servox-25.3.0.dist-info/WHEEL
servox-25.3.0.dist-info/entry_points.txt
servox-25.3.0.dist-info/RECORD
