Metadata-Version: 2.1
Name: servox
Version: 25.3.0
Summary: Opsani Servo: The Next Generation
Home-page: https://opsani.com/
License: Apache-2.0
Author: Blake Watters
Author-email: blake@opsani.com
Requires-Python: >=3.9,<3.13
Classifier: License :: OSI Approved :: Apache Software License
Classifier: Programming Language :: Python :: 3
Classifier: Programming Language :: Python :: 3.9
Classifier: Programming Language :: Python :: 3.10
Classifier: Programming Language :: Python :: 3.11
Classifier: Programming Language :: Python :: 3.12
Requires-Dist: Authlib (>=1.1.0,<2.0.0)
Requires-Dist: aiofiles (>=23.1.0,<24.0.0)
Requires-Dist: backoff (>=2.2.1,<3.0.0)
Requires-Dist: bullet (>=2.1.0,<3.0.0)
Requires-Dist: colorama (>=0.4.4,<0.5.0)
Requires-Dist: curlify2 (>=1.0.0,<2.0.0)
Requires-Dist: devtools (>=0.10.0,<0.11.0)
Requires-Dist: httpx (>=0.23.0,<0.24.0)
Requires-Dist: jsonschema (>=4.17.3,<5.0.0)
Requires-Dist: kubernetes_asyncio (>=22.6.5,<23.0.0)
Requires-Dist: loguru (>=0.6.0,<0.7.0)
Requires-Dist: orjson (>=3.9.15,<4.0.0)
Requires-Dist: pyaml (>=21.10.1,<22.0.0)
Requires-Dist: pydantic (>=1.9.0,<2.0.0)
Requires-Dist: pyfiglet (>=0.8.post1,<0.9)
Requires-Dist: pygments (>=2.6.1,<3.0.0)
Requires-Dist: python-dateutil (>=2.8.2,<3.0.0)
Requires-Dist: python-dotenv (>=1.0.0,<2.0.0)
Requires-Dist: python-ulid (>=2.4.0.post0,<3.0.0)
Requires-Dist: pytz (>=2022.7.1,<2023.0.0)
Requires-Dist: semver (>=3.0.2,<4.0.0)
Requires-Dist: tabulate (>=0.9.0,<0.10.0)
Requires-Dist: timeago (>=1.0.14,<2.0.0)
Requires-Dist: toml (>=0.10.2,<0.11.0)
Requires-Dist: typer (>=0.7.0,<0.8.0)
Requires-Dist: uvloop (>=0.18.0,<0.19.0)
Requires-Dist: watchfiles (>=0.18.1,<0.19.0)
Project-URL: Repository, https://github.com/opsani/servox
